series_kafka/__init__.py
series_kafka/contracts/__init__.py
series_kafka/contracts/base.py
series_kafka/core/__init__.py
series_kafka/core/config.py
series_kafka/core/consumer.py
series_kafka/core/dlq.py
series_kafka/core/field_extractor.py
series_kafka/core/message.py
series_kafka/core/producer.py
series_kafka/core/topic.py
series_kafka/exceptions.py
series_kafka/middleware/__init__.py
series_kafka/py.typed
series_kafka/schema/__init__.py
series_kafka/schema/serializer.py
series_kafka/schema/validator.py
series_kafka/serializers/__init__.py
series_kafka_topics/__init__.py
series_kafka_topics/messages/__init__.py
series_kafka_topics/messages/schemas.py
series_kafka_topics/posts/__init__.py
series_kafka_topics/posts/schemas.py
series_kafka_topics/users/__init__.py
series_kafka_topics/users/schemas.py
series_kafka-1.0.1.dist-info/METADATA
series_kafka-1.0.1.dist-info/WHEEL
series_kafka-1.0.1.dist-info/licenses/LICENSE
series_kafka-1.0.1.dist-info/RECORD
