Metadata-Version: 2.4
Name: series-kafka
Version: 1.0.1
Summary: Type-safe async Kafka SDK for Python microservices in the Series platform
License: MIT
License-File: LICENSE
Keywords: kafka,async,microservices,event-streaming
Author: Series Engineering
Author-email: engineering@series.io
Requires-Python: >=3.12,<4.0
Classifier: License :: OSI Approved :: MIT License
Classifier: Programming Language :: Python :: 3
Classifier: Programming Language :: Python :: 3.12
Classifier: Programming Language :: Python :: 3.13
Classifier: Programming Language :: Python :: 3.14
Requires-Dist: aiokafka (>=0.10.0,<0.11.0)
Requires-Dist: email-validator (>=2.0.0,<3.0.0)
Requires-Dist: httpx (>=0.25.0,<0.26.0)
Requires-Dist: opentelemetry-api (>=1.21.0,<2.0.0)
Requires-Dist: opentelemetry-exporter-otlp (>=1.21.0,<2.0.0)
Requires-Dist: opentelemetry-sdk (>=1.21.0,<2.0.0)
Requires-Dist: pydantic (>=2.5.0,<3.0.0)
Project-URL: Homepage, https://github.com/series/kafka-sdk-python
